matio/__init__.py
matio/matio.py
matio/subsystem/__init__.py
matio/subsystem/subsys.py
matio/utils/__init__.py
matio/utils/matclass.py
matio/utils/matconvert.py
matio/utils/matheaders.py
matio/utils/matutils.py
matio/utils/converters/matenum.py
matio/utils/converters/matmap.py
matio/utils/converters/matstring.py
matio/utils/converters/mattables.py
matio/utils/converters/mattimes.py
matio/v5/__init__.py
matio/v5/_mio5_utils.c
matio/v5/_mio5_utils.cpython-313-x86_64-linux-gnu.so
matio/v5/_mio5_utils.pyx
matio/v5/_pyalloc.pxd
matio/v5/_streams.c
matio/v5/_streams.cpython-313-x86_64-linux-gnu.so
matio/v5/_streams.pxd
matio/v5/_streams.pyx
matio/v5/matio5_params.py
matio/v5/matreader5.py
matio/v5/matwriter5.py
matio/v5/numpy_rephrasing.h
matio/v7/__init__.py
matio/v7/matreader7.py
matio/v7/matwriter7.py
mat_io-0.6.2.dist-info/METADATA
mat_io-0.6.2.dist-info/WHEEL
mat_io-0.6.2.dist-info/top_level.txt
mat_io-0.6.2.dist-info/RECORD
mat_io-0.6.2.dist-info/licenses/LICENSE
