Metadata-Version: 2.4
Name: mat-io
Version: 0.6.2
Summary: A package for reading MATLAB .mat files, with support for MATLAB datatypes like table and string
Author-email: foreverallama <klockatoo@gmail.com>
License-Expression: BSD-3-Clause
Project-URL: Homepage, https://github.com/foreverallama/matio
Project-URL: Repository, https://github.com/foreverallama/matio
Project-URL: Issues, https://github.com/foreverallama/matio
Keywords: MATLAB,mat,io
Classifier: Intended Audience :: Developers
Classifier: Topic :: Scientific/Engineering
Requires-Python: >=3.11
License-File: LICENSE
Requires-Dist: scipy>=1.15.0
Requires-Dist: numpy>=2.2.2
Requires-Dist: pandas>=2.2.0
Requires-Dist: h5py>=3.13.0
Dynamic: license-file
